byted_seed_models/__init__.py
byted_seed_models-0.0.1.dist-info/METADATA
byted_seed_models-0.0.1.dist-info/WHEEL
byted_seed_models-0.0.1.dist-info/top_level.txt
byted_seed_models-0.0.1.dist-info/RECORD
